simple_rl_pack/__init__.py
simple_rl_pack/bandit.py
simple_rl_pack_kritarth04-0.0.1.dist-info/METADATA
simple_rl_pack_kritarth04-0.0.1.dist-info/WHEEL
simple_rl_pack_kritarth04-0.0.1.dist-info/top_level.txt
simple_rl_pack_kritarth04-0.0.1.dist-info/RECORD
