Metadata-Version: 2.4
Name: simple-rl-pack-Kritarth04
Version: 0.0.1
Summary: A very simple Epsilon-Greedy Bandit RL example package
Author-email: Kritarth Ghosh <kritarthg04@gmail.com>
Project-URL: Homepage, https://github.com/your-username/my_rl_project
Project-URL: Bug Tracker, https://github.com/your-username/my_rl_project/issues
Classifier: Programming Language :: Python :: 3
Classifier: License :: OSI Approved :: MIT License
Classifier: Operating System :: OS Independent
Classifier: Topic :: Scientific/Engineering :: Artificial Intelligence
Requires-Python: >=3.7
